banner_hahahellooo/__init__.py
banner_hahahellooo/banner.py
banner_hahahellooo-0.5.5.dist-info/METADATA
banner_hahahellooo-0.5.5.dist-info/WHEEL
banner_hahahellooo-0.5.5.dist-info/entry_points.txt
banner_hahahellooo-0.5.5.dist-info/top_level.txt
banner_hahahellooo-0.5.5.dist-info/RECORD
