Metadata-Version: 2.1
Name: banner_hahahellooo
Version: 0.5.5
Summary: Banner Output Program
Author-email: hahahellooo <hahahello777@gmail.com>
License: MIT
Project-URL: Homepage, http://github.com/hahahellooo/banner_hahahellooo
Project-URL: Issues, http://github.com/hahahellooo/banner_hahahellooo/issues
Requires-Python: >=3.9
Requires-Dist: pyfiglet >=1.0.2
